mlosvarstore/__init__.py
mlosvarstore/utilities.py
mlosvarstore/varstore.py
mlosvarstore-0.0.3.dist-info/METADATA
mlosvarstore-0.0.3.dist-info/WHEEL
mlosvarstore-0.0.3.dist-info/top_level.txt
mlosvarstore-0.0.3.dist-info/RECORD
