Metadata-Version: 2.1
Name: mlosvarstore
Version: 0.0.3
Summary: mlOS VariableStore Package
Home-page: UNKNOWN
Author: Padma Polash Paul
Author-email: ppaul@dpami.com
License: Braintoy@2021
Platform: UNKNOWN
Classifier: Development Status :: 1 - Planning
Classifier: Intended Audience :: Science/Research
Classifier: License :: OSI Approved :: BSD License
Classifier: Operating System :: POSIX :: Linux
Classifier: Programming Language :: Python :: 3.6
